Classfile /media/data/Work/espressoprogrammer-code/competition/target/classes/com/espressoprogrammer/competition/primitives/ByteCompetition.class
  Last modified Jan 15, 2016; size 674 bytes
  MD5 checksum dc7ab491af922472fb32454267757102
  Compiled from "ByteCompetition.java"
public class com.espressoprogrammer.competition.primitives.Competition
  minor version: 0
  major version: 52
  flags: ACC_PUBLIC, ACC_SUPER
Constant pool:
   #1 = Methodref          #5.#29         // java/lang/Object."<init>":()V
   #2 = Long               40l
   #4 = Class              #30            // com/espressoprogrammer/competition/primitives/ByteCompetition
   #5 = Class              #31            // java/lang/Object
   #6 = Utf8               <init>
   #7 = Utf8               ()V
   #8 = Utf8               Code
   #9 = Utf8               LineNumberTable
  #10 = Utf8               LocalVariableTable
  #11 = Utf8               this
  #12 = Utf8               Lcom/espressoprogrammer/competition/primitives/ByteCompetition;
  #13 = Utf8               main
  #14 = Utf8               ([Ljava/lang/String;)V
  #15 = Utf8               args
  #16 = Utf8               [Ljava/lang/String;
  #17 = Utf8               byteVal
  #18 = Utf8               B
  #19 = Utf8               shortVal
  #20 = Utf8               S
  #21 = Utf8               intVal
  #22 = Utf8               I
  #23 = Utf8               longVal
  #24 = Utf8               J
  #25 = Utf8               Exceptions
  #26 = Class              #32            // java/lang/InterruptedException
  #27 = Utf8               SourceFile
  #28 = Utf8               ByteCompetition.java
  #29 = NameAndType        #6:#7          // "<init>":()V
  #30 = Utf8               com/espressoprogrammer/competition/primitives/ByteCompetition
  #31 = Utf8               java/lang/Object
  #32 = Utf8               java/lang/InterruptedException
{
  public com.espressoprogrammer.competition.primitives.Competition();
    descriptor: ()V
    flags: ACC_PUBLIC
    Code:
      stack=1, locals=1, args_size=1
         0: aload_0
         1: invokespecial #1                  // Method java/lang/Object."<init>":()V
         4: return
      LineNumberTable:
        line 3: 0
      LocalVariableTable:
        Start  Length  Slot  Name   Signature
            0       5     0  this   Lcom/espressoprogrammer/competition/primitives/ByteCompetition;

  public static void main(java.lang.String...) throws java.lang.InterruptedException;
    descriptor: ([Ljava/lang/String;)V
    flags: ACC_PUBLIC, ACC_STATIC, ACC_VARARGS
    Code:
      stack=2, locals=6, args_size=1
         0: bipush        10
         2: istore_1
         3: bipush        20
         5: istore_2
         6: bipush        30
         8: istore_3
         9: ldc2_w        #2                  // long 40l
        12: lstore        4
        14: return
      LineNumberTable:
        line 6: 0
        line 7: 3
        line 8: 6
        line 9: 9
        line 10: 14
      LocalVariableTable:
        Start  Length  Slot  Name   Signature
            0      15     0  args   [Ljava/lang/String;
            3      12     1 byteVal   B
            6       9     2 shortVal   S
            9       6     3 intVal   I
           14       1     4 longVal   J
    Exceptions:
      throws java.lang.InterruptedException
}
SourceFile: "ByteCompetition.java"
